odoo8_addon_partner_academic_title-8.0.1.0.0.99.dev16-py2.7-nspkg.pth
odoo8_addon_partner_academic_title-8.0.1.0.0.99.dev16.dist-info/METADATA
odoo8_addon_partner_academic_title-8.0.1.0.0.99.dev16.dist-info/RECORD
odoo8_addon_partner_academic_title-8.0.1.0.0.99.dev16.dist-info/WHEEL
odoo8_addon_partner_academic_title-8.0.1.0.0.99.dev16.dist-info/namespace_packages.txt
odoo8_addon_partner_academic_title-8.0.1.0.0.99.dev16.dist-info/top_level.txt
odoo_addons/partner_academic_title/README.rst
odoo_addons/partner_academic_title/__init__.py
odoo_addons/partner_academic_title/__openerp__.py
odoo_addons/partner_academic_title/data/partner_academic_title_data.xml
odoo_addons/partner_academic_title/i18n/de.po
odoo_addons/partner_academic_title/i18n/es.po
odoo_addons/partner_academic_title/i18n/eu.po
odoo_addons/partner_academic_title/i18n/fi.po
odoo_addons/partner_academic_title/i18n/it.po
odoo_addons/partner_academic_title/i18n/partner_academic_title.pot
odoo_addons/partner_academic_title/i18n/sl.po
odoo_addons/partner_academic_title/models/__init__.py
odoo_addons/partner_academic_title/models/partner_academic_title.py
odoo_addons/partner_academic_title/models/res_partner.py
odoo_addons/partner_academic_title/security/ir.model.access.csv
odoo_addons/partner_academic_title/static/description/icon.png
odoo_addons/partner_academic_title/views/partner_academic_title_view.xml
odoo_addons/partner_academic_title/views/res_partner_view.xml
